score_analysis/__init__.py
score_analysis/applications/__init__.py
score_analysis/applications/doc_fraud.py
score_analysis/cm.py
score_analysis/experimental/__init__.py
score_analysis/experimental/datasets.py
score_analysis/experimental/roc_ci.py
score_analysis/group_scores.py
score_analysis/metrics.py
score_analysis/roc_curve.py
score_analysis/scores.py
score_analysis/showbias.py
score_analysis/showbias_plotting.py
score_analysis/utils.py
score_analysis-0.3.0.dist-info/LICENSE
score_analysis-0.3.0.dist-info/METADATA
score_analysis-0.3.0.dist-info/WHEEL
score_analysis-0.3.0.dist-info/RECORD
