Metadata-Version: 2.1
Name: score-analysis
Version: 0.3.0
Summary: Library to evaluate models
Author: Martins Bruveris
Author-email: martins.bruveris@gmx.com
Requires-Python: >=3.9,<3.13
Classifier: Programming Language :: Python :: 3
Classifier: Programming Language :: Python :: 3.9
Classifier: Programming Language :: Python :: 3.10
Classifier: Programming Language :: Python :: 3.11
Classifier: Programming Language :: Python :: 3.12
Requires-Dist: numpy
Requires-Dist: pandas
Requires-Dist: scipy
Requires-Dist: tabulate
